polarsgrid/__init__.py
polarsgrid-0.3.0.dist-info/licenses/LICENSE
polarsgrid-0.3.0.dist-info/WHEEL
polarsgrid-0.3.0.dist-info/METADATA
polarsgrid-0.3.0.dist-info/RECORD
