Metadata-Version: 2.4
Name: polarsgrid
Version: 0.3.0
Summary: Expand grid functionality using Polars
Author: Erik-Jan van Kesteren
Author-email: Erik-Jan van Kesteren <erikjanvankesteren@pm.me>
License-Expression: MIT
License-File: LICENSE
Classifier: Programming Language :: Python :: 3.11
Classifier: Programming Language :: Python :: 3.12
Classifier: Programming Language :: Python :: 3.13
Classifier: Operating System :: OS Independent
Classifier: Development Status :: 4 - Beta
Requires-Dist: polars>=1.31.0
Requires-Python: >=3.11
Project-URL: Homepage, https://github.com/vankesteren/polarsgrid
Project-URL: Issues, https://github.com/vankesteren/polarsgrid/issues
